corallium/__init__.py
corallium/_runtime_type_check_setup.py
corallium/file_helpers.py
corallium/log.py
corallium/loggers/__init__.py
corallium/loggers/plain_printer.py
corallium/loggers/rich_printer.py
corallium/loggers/structlog_logger/__init__.py
corallium/loggers/structlog_logger/_structlog_logger.py
corallium/loggers/styles.py
corallium/pretty_process.py
corallium/py.typed
corallium/shell.py
corallium/tomllib.py
corallium-2.1.1.dist-info/LICENSE
corallium-2.1.1.dist-info/METADATA
corallium-2.1.1.dist-info/WHEEL
corallium-2.1.1.dist-info/RECORD
