Metadata-Version: 2.1
Name: corallium
Version: 2.1.1
Summary: Shared functionality for the calcipy-ecosystem
Home-page: https://github.com/kyleking/corallium
License: MIT
Keywords: calcipy_template
Author: Kyle King
Author-email: dev.act.kyle@gmail.com
Requires-Python: >=3.9.13,<4.0.0
Classifier: Development Status :: 4 - Beta
Classifier: License :: OSI Approved :: MIT License
Classifier: Operating System :: OS Independent
Classifier: Programming Language :: Python :: 3
Classifier: Programming Language :: Python :: 3.10
Classifier: Programming Language :: Python :: 3.11
Classifier: Programming Language :: Python :: 3.12
Classifier: Programming Language :: Python :: 3.13
Classifier: Programming Language :: Python :: 3.9
Requires-Dist: beartype (>=0.19.0)
Requires-Dist: rich (>=13.9.2)
Requires-Dist: tomli (>=2.0.2) ; python_version < "3.11"
Requires-Dist: typing-extensions (>=4.12.2)
Project-URL: Bug Tracker, https://github.com/kyleking/corallium/issues
Project-URL: Changelog, https://github.com/kyleking/corallium/blob/main/docs/docs/CHANGELOG.md
Project-URL: Documentation, https://corallium.kyleking.me
Project-URL: Repository, https://github.com/kyleking/corallium
